{
  "+0_fishing_zone@dawn": "+0_fishing_zone@dawn.png",
  "+0_fishing_zone@day": "+0_fishing_zone@day.png",
  "+0_fishing_zone@dusk": "+0_fishing_zone@dusk.png",
  "+0_fishing_zone@night": "+0_fishing_zone@night.png",
  "+14_a_eagle_island@dawn": "+14_a_eagle_island@dawn.png",
  "+14_a_eagle_island@day": "+14_a_eagle_island@day.png",
  "+14_a_eagle_island@dusk": "+14_a_eagle_island@dusk.png",
  "+14_a_eagle_island@night": "+14_a_eagle_island@night.png",
  "+14_eagle_nest": "+14_eagle_nest.png",
  "+14_eagle_nest_chick": "+14_eagle_nest_chick.png",
  "+14_otter": "+14_otter2.png",
  "+17_rock.seals": "+17_rock.seals.png",
  "+18_front_rock_group@dawn": "+18_front_rock_group@dawn.png",
  "+18_front_rock_group@day": "+18_front_rock_group@day.png",
  "+18_front_rock_group@dusk": "+18_front_rock_group@dusk.png",
  "+18_front_rock_group@night": "+18_front_rock_group@night.png",
  "+20_beaver_dam_01@dawn": "+20_Beaver_Dam_01@dawn.png",
  "+20_beaver_dam_01@day": "+20_Beaver_Dam_01@day.png",
  "+20_beaver_dam_01@dusk": "+20_Beaver_Dam_01@dusk.png",
  "+20_beaver_dam_01@night": "+20_Beaver_Dam_01@night.png",
  "+22_beaver": "+22_beaver.png",
  "+24_beaver_dam_02@dawn": "+24_Beaver_Dam_02@dawn.png",
  "+24_beaver_dam_02@day": "+24_Beaver_Dam_02@day.png",
  "+24_beaver_dam_02@dusk": "+24_Beaver_Dam_02@dusk.png",
  "+24_beaver_dam_02@night": "+24_Beaver_Dam_02@night.png",
  "+28_beaver_dam_03_copy_5@dawn": "+28_Beaver_Dam_03_copy_5@dawn.png",
  "+28_beaver_dam_03_copy_5@day": "+28_Beaver_Dam_03_copy_5@day.png",
  "+28_beaver_dam_03_copy_5@dusk": "+28_Beaver_Dam_03_copy_5@dusk.png",
  "+28_beaver_dam_03_copy_5@night": "+28_Beaver_Dam_03_copy_5@night.png",
  "+32_beaver_dam@dawn": "+32_Beaver_Dam@dawn.png",
  "+32_beaver_dam@day": "+32_Beaver_Dam@day.png",
  "+32_beaver_dam@dusk": "+32_Beaver_Dam@dusk.png",
  "+32_beaver_dam@night": "+32_Beaver_Dam@night.png",
  "+37_rock.farseals": "+37_rock.farseals.png",
  "+71_northernights@night": "+71_northern_lights@night.png",
  "+9_rock.seals": "+9_rock.seals.png",
  "+9_rock.seals_a": "+9_rock.seals_a.png",
  "americanshad": "AmericanShad_UI.png",
  "arcticgrayling": "ArcticGrayling_UI.png",
  "arctic_char": "Arctic_Char_UI.png",
  "atlanticsalmon": "AtlanticSalmon_UI.png",
  "bluegill_sunfish": "Bluegill-Sunfish_S.png",
  "bluegillunfish": "Bluegill_Sunfish_UI.png",
  "brooktrout": "BrookTrout_UI.png",
  "browntrout": "BrownTrout_UI.png",
  "bullheadcatfish": "BullheadCatfish_UI.png",
  "burbot": "Burbot_UI.png",
  "capelin": "Capelin_UI.png",
  "carp": "Carp0.png",
  "catch_with_fish": "Catch_With_Fish0.png",
  "channelcatfish": "ChannelCatfish_UI.png",
  "channel_catfish": "Channel_Catfish0.png",
  "chinooksalmon": "ChinookSalmon_UI.png",
  "chumsalmon": "ChumSalmon_UI.png",
  "cisco": "Cisco_UI.png",
  "cohosalmon": "CohoSalmon_UI.png",
  "commoncarp": "CommonCarp_UI.png",
  "crappie": "Crappie_UI.png",
  "creekchub": "CreekChub_UI.png",
  "cutthroat": "Cutthroat0.png",
  "cutthroattrout": "CutthroatTrout_UI.png",
  "eulachon": "Eulachon_UI.png",
  "goldeye": "Goldeye_UI.png",
  "greenlandhalibut": "GreenlandHalibut_UI.png",
  "humpbackwhitefish": "HumpbackWhitefish_UI.png",
  "hybridstripedbass": "HybridStripedBass_UI.png",
  "icearcticchar": "IceArcticChar_UI.png",
  "icechannelcatfish": "IceChannelCatfish_UI.png",
  "icelaketrout": "IceLakeTrout_UI.png",
  "icelargemouthbass": "IceLargemouthBass_UI.png",
  "icemuskie": "IceMuskie_UI.png",
  "icenorthernpike": "IceNorthernPike_UI.png",
  "icesmallmouthbass": "IceSmallmouthBass_UI.png",
  "icetigermuskie": "IceTigerMuskie_UI.png",
  "icewalleye": "IceWalleye_UI.png",
  "iceyellowperch": "IceYellowPerch_UI.png",
  "laketrout": "LakeTrout0.png",
  "lakewhitefish": "LakeWhitefish_UI.png",
  "lake_trout": "Lake_Trout_UI.png",
  "largemouth": "Largemouth0.png",
  "largemouthbass": "LargemouthBass_UI.png",
  "largescalesucker": "LargescaleSucker_UI.png",
  "lingcod": "Lingcod_UI.png",
  "longnosedace": "LongnoseDace_UI.png",
  "longnosesucker": "LongnoseSucker_UI.png",
  "lose_fishong": "Lose_Fish_Long0.png",
  "masusalmon": "MasuSalmon_UI.png",
  "mooneye": "Mooneye_UI.png",
  "muskie": "Muskie_UI.png",
  "northernpike": "NorthernPike_UI.png",
  "northernsquawfish": "NorthernSquawfish_UI.png",
  "pacifichalibut": "PacificHalibut_UI.png",
  "pacificherring": "PacificHerring_UI.png",
  "peamouth": "Peamouth_UI.png",
  "pike": "Pike0.png",
  "pinksalmon": "PinkSalmon_UI.png",
  "rainbowtrout": "RainbowTrout_UI.png",
  "rockbass": "RockBass_UI.png",
  "roundwhitefish": "RoundWhitefish_UI.png",
  "shortheadredhorse": "ShortheadRedhorse_UI.png",
  "smallmouth_bass": "Smallmouth_Bass_UI.png",
  "sockeyesalmon": "SockeyeSalmon_UI.png",
  "steelheadtrout": "SteelheadTrout_UI.png",
  "stripedbass": "StripedBass_UI.png",
  "threadfinhad": "Threadfin_Shad_UI.png",
  "tigermuskie": "TigerMuskie0.png",
  "tigertrout": "TigerTrout_UI.png",
  "walleye": "Walleye_UI.png",
  "whitebass": "WhiteBass_UI.png",
  "whitesturgeon": "WhiteSturgeon_UI.png",
  "whitesucker": "WhiteSucker_UI.png",
  "whiteturgeon": "White_Sturgeon0.png",
  "yellowperch": "YellowPerch_UI.png",
  "yelloweyerockfish": "YelloweyeRockfish_UI.png",
  "_15_beaver": "_15_beaver.png",
  "_22_jumping_otters": "_22_jumping_otters01.png",
  "_22_otter_pup_": "_22_otter_pup_01.png",
  "_22_ulfallenog.logotter_a": "_22_ulfallen_log.LogOtter_A.png",
  "_28_otter": "_28_otter.png",
  "_30_fg_otter_on_rock": "_30_fg_otter_on_rock.png",
  "_34_fg_beaver_dameft@dawn": "_34_FG_Beaver_Dam_Left@dawn.png",
  "_34_fg_beaver_dameft@day": "_34_FG_Beaver_Dam_Left@day.png",
  "_34_fg_beaver_dameft@dusk": "_34_FG_Beaver_Dam_Left@dusk.png",
  "_34_fg_beaver_dameft@night": "_34_FG_Beaver_Dam_Left@night.png",
  "_35_eagle_nest.dad": "_35_eagle_nest.dad.png",
  "_35_eagle_nest.mum": "_35_eagle_nest.mum.png",
  "_35_eagle_nest@dawn": "_35_eagle_nest@dawn.png",
  "_35_eagle_nest@day": "_35_eagle_nest@day.png",
  "_35_eagle_nest@dusk": "_35_eagle_nest@dusk.png",
  "_35_eagle_nest@night": "_35_eagle_nest@night.png",
  "_35_fg_rock_02@dawn": "_35_fg_rock_02@dawn.png",
  "_35_fg_rock_02@day": "_35_fg_rock_02@day.png",
  "_35_fg_rock_02@dusk": "_35_fg_rock_02@dusk.png",
  "_35_fg_rock_02@night": "_35_fg_rock_02@night.png",
  "atlanticalmon": "atlantic_salmon.png",
  "chinookalmon": "chinook_salmon.png",
  "common_carp": "common_carp.png",
  "cutthroat_trout": "cutthroat_trout.png",
  "largemouth_bass": "largemouth_bass.png",
  "northern_pike": "northern_pike.png",
  "pacific_halibut": "pacific_halibut.png",
  "striped_bass": "striped_bass.png",
  "ui_journal_current_indicator": "ui_journal_current_indicator.png",
  "ui_journalocation": "ui_journal_location.png",
  "uiettings_tab_journals": "ui_settings_tab_journals.png"
}